get_metars/__init__.py
get_metars/__main__.py
get_metars/get.py
get_metars/sanitize.py
get_metars-0.5.1.dist-info/LICENSE
get_metars-0.5.1.dist-info/METADATA
get_metars-0.5.1.dist-info/WHEEL
get_metars-0.5.1.dist-info/entry_points.txt
get_metars-0.5.1.dist-info/RECORD
